odoo/addons/sale_order_line_no_print/README.rst
odoo/addons/sale_order_line_no_print/__init__.py
odoo/addons/sale_order_line_no_print/__manifest__.py
odoo/addons/sale_order_line_no_print/i18n/sale_order_line_no_print.pot
odoo/addons/sale_order_line_no_print/models/__init__.py
odoo/addons/sale_order_line_no_print/models/account_move.py
odoo/addons/sale_order_line_no_print/models/sale_order.py
odoo/addons/sale_order_line_no_print/readme/CONTEXT.md
odoo/addons/sale_order_line_no_print/readme/CONTRIBUTORS.md
odoo/addons/sale_order_line_no_print/readme/DESCRIPTION.md
odoo/addons/sale_order_line_no_print/readme/USAGE.md
odoo/addons/sale_order_line_no_print/static/description/icon.png
odoo/addons/sale_order_line_no_print/static/description/index.html
odoo/addons/sale_order_line_no_print/views/account_move_views.xml
odoo/addons/sale_order_line_no_print/views/report_invoice_document.xml
odoo/addons/sale_order_line_no_print/views/report_saleorder_document.xml
odoo/addons/sale_order_line_no_print/views/sale_order_views.xml
odoo_addon_sale_order_line_no_print-16.0.1.0.1.dist-info/METADATA
odoo_addon_sale_order_line_no_print-16.0.1.0.1.dist-info/WHEEL
odoo_addon_sale_order_line_no_print-16.0.1.0.1.dist-info/top_level.txt
odoo_addon_sale_order_line_no_print-16.0.1.0.1.dist-info/RECORD
